{
    "entities": [
        {
            "nid": "8062",
            "path": "/erialad/meeskonnajuht",
            "id": "studyProgramme",
            "fieldAccreditationStatus": null,
            "fieldAccreditationValidUntil": null,
            "fieldAdmissionBeginDate": "1718744400",
            "fieldAdmissionEndDate": "1723237140",
            "fieldAdmissionId": "15680",
            "fieldAdmissionLink": "https://sais.ee/AdmissionSearch/View/15680",
            "fieldAmount": "60",
            "fieldAmountUnit": "EKAP",
            "fieldDegreeOrDiplomaAwarded": null,
            "fieldDuration": "12",
            "fieldEducationalInstitution": {
                "9251": {
                    "fieldEducationalInstitutionTy": {
                        "2364": "Kutseõppeasutus"
                    },
                    "fieldOwnershipType": {
                        "2033": "Riigiomandus"
                    },
                    "fieldSchoolContactEmail": "info@tmk.edu.ee",
                    "fieldSchoolContactPhone": "56281688",
                    "fieldSchoolLocation": {
                        "6831": {
                            "fieldAddress": "A. H. Tammsaare tee 147, Mustamäe linnaosa, Tallinn, Harju maakond",
                            "fieldCoordinates": {
                                "name": "A. H. Tammsaare tee 147, Mustamäe linnaosa, Tallinn, Harju maakond",
                                "lat": "59.409662",
                                "lon": "24.67088",
                                "zoom": null,
                                "type": null,
                                "width": null,
                                "height": null,
                                "marker": null,
                                "traffic": null,
                                "marker_icon": null,
                                "controls": null,
                                "infowindow": null
                            },
                            "fieldLocationType": "L",
                            "fieldSchoolLocation": {
                                "70": "Mustamäe linnaosa"
                            },
                            "paraType": "school_location"
                        }
                    },
                    "fieldSchoolWebpageAddress": "http://www.tmk.edu.ee",
                    "fieldSpecialClass": null,
                    "fieldTeachingLanguage": {
                        "1689": "eesti keel",
                        "1691": "vene keel"
                    },
                    "uid": "1",
                    "title": "Tallinna Majanduskool",
                    "created": "1538403795"
                }
            },
            "fieldIscedfBoard": {
                "2463": "Ärindus, haldus ja õigus"
            },
            "fieldIscedfDetailed": {
                "2469": "Juhtimine ja haldus"
            },
            "fieldIscedfNarrow": {
                "2464": "Ärindus ja haldus"
            },
            "fieldMetatags": null,
            "fieldMinimumRequiredEducation": {
                "3226": "üldkeskharidus (310)"
            },
            "fieldPracticalTrainingAmount": "22",
            "fieldSchoolAddress": "A. H. Tammsaare tee 147, Mustamäe linnaosa, Tallinn, Harju maakond",
            "fieldSchoolSearchAddress": "Mustamäe linnaosa, Tallinn, Harju maakond",
            "fieldSchoolWebsite": "http://www.tmk.edu.ee",
            "fieldShortDescription": null,
            "fieldSpecialization": "määramata",
            "fieldStudyProgrammeLevel": {
                "2013": "Kutseõpe keskhariduse baasil"
            },
            "fieldStudyProgrammeType": {
                "644": "Kutsehariduse õppekava"
            },
            "fieldTeachingLanguage": {
                "1689": "eesti keel"
            },
            "uid": "1",
            "title": "Meeskonnajuht",
            "created": "1537777040"
        },
        {
            "nid": "8063",
            "path": "/erialad/e-turundusspetsialist",
            "id": "studyProgramme",
            "fieldAccreditationStatus": null,
            "fieldAccreditationValidUntil": null,
            "fieldAdmissionBeginDate": null,
            "fieldAdmissionEndDate": null,
            "fieldAdmissionId": null,
            "fieldAdmissionLink": null,
            "fieldAmount": "60",
            "fieldAmountUnit": "EKAP",
            "fieldDegreeOrDiplomaAwarded": null,
            "fieldDuration": "12",
            "fieldEducationalInstitution": {
                "9251": {
                    "fieldEducationalInstitutionTy": {
                        "2364": "Kutseõppeasutus"
                    },
                    "fieldOwnershipType": {
                        "2033": "Riigiomandus"
                    },
                    "fieldSchoolContactEmail": "info@tmk.edu.ee",
                    "fieldSchoolContactPhone": "56281688",
                    "fieldSchoolLocation": {
                        "6831": {
                            "fieldAddress": "A. H. Tammsaare tee 147, Mustamäe linnaosa, Tallinn, Harju maakond",
                            "fieldCoordinates": {
                                "name": "A. H. Tammsaare tee 147, Mustamäe linnaosa, Tallinn, Harju maakond",
                                "lat": "59.409662",
                                "lon": "24.67088",
                                "zoom": null,
                                "type": null,
                                "width": null,
                                "height": null,
                                "marker": null,
                                "traffic": null,
                                "marker_icon": null,
                                "controls": null,
                                "infowindow": null
                            },
                            "fieldLocationType": "L",
                            "fieldSchoolLocation": {
                                "70": "Mustamäe linnaosa"
                            },
                            "paraType": "school_location"
                        }
                    },
                    "fieldSchoolWebpageAddress": "http://www.tmk.edu.ee",
                    "fieldSpecialClass": null,
                    "fieldTeachingLanguage": {
                        "1689": "eesti keel",
                        "1691": "vene keel"
                    },
                    "uid": "1",
                    "title": "Tallinna Majanduskool",
                    "created": "1538403795"
                }
            },
            "fieldIscedfBoard": {
                "2463": "Ärindus, haldus ja õigus"
            },
            "fieldIscedfDetailed": {
                "2471": "Turundus ja reklaam"
            },
            "fieldIscedfNarrow": {
                "2464": "Ärindus ja haldus"
            },
            "fieldMetatags": null,
            "fieldMinimumRequiredEducation": null,
            "fieldPracticalTrainingAmount": "18",
            "fieldSchoolAddress": "A. H. Tammsaare tee 147, Mustamäe linnaosa, Tallinn, Harju maakond",
            "fieldSchoolSearchAddress": "Mustamäe linnaosa, Tallinn, Harju maakond",
            "fieldSchoolWebsite": "http://www.tmk.edu.ee",
            "fieldShortDescription": null,
            "fieldSpecialization": "määramata",
            "fieldStudyProgrammeLevel": {
                "2013": "Kutseõpe keskhariduse baasil"
            },
            "fieldStudyProgrammeType": {
                "644": "Kutsehariduse õppekava"
            },
            "fieldTeachingLanguage": {
                "1689": "eesti keel"
            },
            "uid": "1",
            "title": "E-turundusspetsialist",
            "created": "1537777040"
        },
        {
            "nid": "8077",
            "path": "/erialad/maastikuehitaja-osakutse-haljasalade-hooldaja-2",
            "id": "studyProgramme",
            "fieldAccreditationStatus": null,
            "fieldAccreditationValidUntil": null,
            "fieldAdmissionBeginDate": null,
            "fieldAdmissionEndDate": null,
            "fieldAdmissionId": null,
            "fieldAdmissionLink": null,
            "fieldAmount": "45",
            "fieldAmountUnit": "EKAP",
            "fieldDegreeOrDiplomaAwarded": null,
            "fieldDuration": "12",
            "fieldEducationalInstitution": {
                "10460": {
                    "fieldEducationalInstitutionTy": {
                        "2364": "Kutseõppeasutus"
                    },
                    "fieldOwnershipType": {
                        "2033": "Riigiomandus"
                    },
                    "fieldSchoolContactEmail": "info@luua.ee",
                    "fieldSchoolContactPhone": "(77) 62 111",
                    "fieldSchoolLocation": {
                        "8035": {
                            "fieldAddress": "Metsakooli/4, Luua küla, Jõgeva vald, Jõgeva maakond",
                            "fieldCoordinates": {
                                "name": "Metsakooli/4, Luua küla, Jõgeva vald, Jõgeva maakond",
                                "lat": "58.654634",
                                "lon": "26.603319",
                                "zoom": null,
                                "type": null,
                                "width": null,
                                "height": null,
                                "marker": null,
                                "traffic": null,
                                "marker_icon": null,
                                "controls": null,
                                "infowindow": null
                            },
                            "fieldLocationType": "L",
                            "fieldSchoolLocation": {
                                "185": "Luua küla"
                            },
                            "paraType": "school_location"
                        }
                    },
                    "fieldSchoolWebpageAddress": "http://www.luua.ee/",
                    "fieldSpecialClass": null,
                    "fieldTeachingLanguage": {
                        "1689": "eesti keel",
                        "1690": "inglise keel",
                        "1691": "vene keel"
                    },
                    "uid": "1",
                    "title": "Luua Metsanduskool",
                    "created": "1538404013"
                }
            },
            "fieldIscedfBoard": {
                "2576": "Põllumajandus, metsandus, kalandus ja veterinaaria"
            },
            "fieldIscedfDetailed": {
                "2580": "Aiandus"
            },
            "fieldIscedfNarrow": {
                "2577": "Põllumajandus"
            },
            "fieldMetatags": null,
            "fieldMinimumRequiredEducation": null,
            "fieldPracticalTrainingAmount": "11",
            "fieldSchoolAddress": "Metsakooli/4, Luua küla, Jõgeva vald, Jõgeva maakond",
            "fieldSchoolSearchAddress": "Luua küla, Jõgeva vald, Jõgeva maakond",
            "fieldSchoolWebsite": "http://www.luua.ee/",
            "fieldShortDescription": null,
            "fieldSpecialization": "määramata",
            "fieldStudyProgrammeLevel": {
                "2373": "Kutseõpe põhihariduse baasil"
            },
            "fieldStudyProgrammeType": {
                "644": "Kutsehariduse õppekava"
            },
            "fieldTeachingLanguage": {
                "1689": "eesti keel"
            },
            "uid": "1",
            "title": "Maastikuehitaja (osakutse haljasalade hooldaja)",
            "created": "1537777041"
        },
        {
            "nid": "8102",
            "path": "/erialad/mehhatroonik-7",
            "id": "studyProgramme",
            "fieldAccreditationStatus": null,
            "fieldAccreditationValidUntil": null,
            "fieldAdmissionBeginDate": "1723496400",
            "fieldAdmissionEndDate": "1724705940",
            "fieldAdmissionId": "15991",
            "fieldAdmissionLink": "https://sais.ee/AdmissionSearch/View/15991",
            "fieldAmount": "180",
            "fieldAmountUnit": "EKAP",
            "fieldDegreeOrDiplomaAwarded": null,
            "fieldDuration": "36",
            "fieldEducationalInstitution": {
                "11825": {
                    "fieldEducationalInstitutionTy": {
                        "1686": "Gümnaasium",
                        "2364": "Kutseõppeasutus",
                        "2371": "Põhikool"
                    },
                    "fieldOwnershipType": {
                        "2033": "Riigiomandus"
                    },
                    "fieldSchoolContactEmail": "ewers@ewers.ee",
                    "fieldSchoolContactPhone": "7850800",
                    "fieldSchoolLocation": {
                        "9398": {
                            "fieldAddress": "Kooli tee 1, Väimela alevik, Võru vald, Võru maakond",
                            "fieldCoordinates": {
                                "name": "Kooli tee 1, Väimela alevik, Võru vald, Võru maakond",
                                "lat": "57.891173",
                                "lon": "27.013394",
                                "zoom": null,
                                "type": null,
                                "width": null,
                                "height": null,
                                "marker": null,
                                "traffic": null,
                                "marker_icon": null,
                                "controls": null,
                                "infowindow": null
                            },
                            "fieldLocationType": "L",
                            "fieldSchoolLocation": {
                                "590": "Väimela alevik"
                            },
                            "paraType": "school_location"
                        }
                    },
                    "fieldSchoolWebpageAddress": "http://www.ewers.ee",
                    "fieldSpecialClass": null,
                    "fieldTeachingLanguage": {
                        "1689": "eesti keel"
                    },
                    "uid": "1",
                    "title": "Võrumaa Haridus- ja Tehnoloogiakeskus",
                    "created": "1538404301"
                }
            },
            "fieldIscedfBoard": {
                "2538": "Tehnika, tootmine ja ehitus"
            },
            "fieldIscedfDetailed": {
                "2546": "Elektroonika ja automaatika"
            },
            "fieldIscedfNarrow": {
                "2539": "Tehnikaalad"
            },
            "fieldMetatags": null,
            "fieldMinimumRequiredEducation": null,
            "fieldPracticalTrainingAmount": "31",
            "fieldSchoolAddress": "Kooli tee 1, Väimela alevik, Võru vald, Võru maakond",
            "fieldSchoolSearchAddress": "Väimela alevik, Võru vald, Võru maakond",
            "fieldSchoolWebsite": "http://www.ewers.ee",
            "fieldShortDescription": null,
            "fieldSpecialization": "määramata",
            "fieldStudyProgrammeLevel": {
                "2012": "Kutsekeskharidusõpe",
                "2373": "Kutseõpe põhihariduse baasil"
            },
            "fieldStudyProgrammeType": {
                "644": "Kutsehariduse õppekava"
            },
            "fieldTeachingLanguage": {
                "1689": "eesti keel"
            },
            "uid": "1",
            "title": "Mehhatroonik",
            "created": "1537777042"
        },
        {
            "nid": "8116",
            "path": "/erialad/kosmeetik-0",
            "id": "studyProgramme",
            "fieldAccreditationStatus": null,
            "fieldAccreditationValidUntil": null,
            "fieldAdmissionBeginDate": "1711918800",
            "fieldAdmissionEndDate": "1722632340",
            "fieldAdmissionId": "14431",
            "fieldAdmissionLink": "https://sais.ee/AdmissionSearch/View/14431",
            "fieldAmount": "120",
            "fieldAmountUnit": "EKAP",
            "fieldDegreeOrDiplomaAwarded": null,
            "fieldDuration": "24",
            "fieldEducationalInstitution": {
                "11411": {
                    "fieldEducationalInstitutionTy": {
                        "2364": "Kutseõppeasutus"
                    },
                    "fieldOwnershipType": {
                        "1688": "Munitsipaal"
                    },
                    "fieldSchoolContactEmail": "info@voco.ee",
                    "fieldSchoolContactPhone": "7361866",
                    "fieldSchoolLocation": {
                        "8984": {
                            "fieldAddress": "Kopli tn 1, Tartu linn, Tartu linn, Tartu maakond",
                            "fieldCoordinates": {
                                "name": "Kopli tn 1, Tartu linn, Tartu linn, Tartu maakond",
                                "lat": "58.3494",
                                "lon": "26.714176",
                                "zoom": null,
                                "type": null,
                                "width": null,
                                "height": null,
                                "marker": null,
                                "traffic": null,
                                "marker_icon": null,
                                "controls": null,
                                "infowindow": null
                            },
                            "fieldLocationType": "L",
                            "fieldSchoolLocation": {
                                "494": "Tartu linn"
                            },
                            "paraType": "school_location"
                        }
                    },
                    "fieldSchoolWebpageAddress": "https://voco.ee",
                    "fieldSpecialClass": null,
                    "fieldTeachingLanguage": {
                        "1689": "eesti keel",
                        "1691": "vene keel"
                    },
                    "uid": "1",
                    "title": "Tartu Rakenduslik Kolledž",
                    "created": "1538404224"
                }
            },
            "fieldIscedfBoard": {
                "2632": "Teenindus"
            },
            "fieldIscedfDetailed": {
                "2636": "Juuksuritöö ja iluteenindus"
            },
            "fieldIscedfNarrow": {
                "2633": "Isikuteenindus"
            },
            "fieldMetatags": null,
            "fieldMinimumRequiredEducation": {
                "3226": "üldkeskharidus (310)"
            },
            "fieldPracticalTrainingAmount": "20",
            "fieldSchoolAddress": "Kopli tn 1, Tartu linn, Tartu linn, Tartu maakond",
            "fieldSchoolSearchAddress": "Tartu linn, Tartu linn, Tartu maakond",
            "fieldSchoolWebsite": "https://voco.ee",
            "fieldShortDescription": null,
            "fieldSpecialization": "määramata",
            "fieldStudyProgrammeLevel": {
                "2013": "Kutseõpe keskhariduse baasil"
            },
            "fieldStudyProgrammeType": {
                "644": "Kutsehariduse õppekava"
            },
            "fieldTeachingLanguage": {
                "1689": "eesti keel"
            },
            "uid": "1",
            "title": "Kosmeetik",
            "created": "1537777044"
        },
        {
            "nid": "8123",
            "path": "/erialad/it-s%C3%BCsteemide-nooremspetsialist-3",
            "id": "studyProgramme",
            "fieldAccreditationStatus": null,
            "fieldAccreditationValidUntil": null,
            "fieldAdmissionBeginDate": null,
            "fieldAdmissionEndDate": null,
            "fieldAdmissionId": null,
            "fieldAdmissionLink": null,
            "fieldAmount": "120",
            "fieldAmountUnit": "EKAP",
            "fieldDegreeOrDiplomaAwarded": null,
            "fieldDuration": "24",
            "fieldEducationalInstitution": {
                "11345": {
                    "fieldEducationalInstitutionTy": {
                        "2364": "Kutseõppeasutus"
                    },
                    "fieldOwnershipType": {
                        "2033": "Riigiomandus"
                    },
                    "fieldSchoolContactEmail": "info@ivkhk.ee",
                    "fieldSchoolContactPhone": "3320381",
                    "fieldSchoolLocation": {
                        "8918": {
                            "fieldAddress": "Tallinna mnt 13, Sillamäe linn, Ida-Viru maakond",
                            "fieldCoordinates": {
                                "name": "Tallinna mnt 13, Sillamäe linn, Ida-Viru maakond",
                                "lat": "59.39098",
                                "lon": "27.793492",
                                "zoom": null,
                                "type": null,
                                "width": null,
                                "height": null,
                                "marker": null,
                                "traffic": null,
                                "marker_icon": null,
                                "controls": null,
                                "infowindow": null
                            },
                            "fieldLocationType": "L",
                            "fieldSchoolLocation": {
                                "485": "Sillamäe linn"
                            },
                            "paraType": "school_location"
                        },
                        "373035": {
                            "fieldAddress": "Kutse tn 13, Jõhvi linn, Jõhvi vald, Ida-Viru maakond",
                            "fieldCoordinates": {
                                "name": "Kutse tn 13, Jõhvi linn, Jõhvi vald, Ida-Viru maakond",
                                "lat": "59.360033",
                                "lon": "27.399148",
                                "zoom": null,
                                "type": null,
                                "width": null,
                                "height": null,
                                "marker": null,
                                "traffic": null,
                                "marker_icon": null,
                                "controls": null,
                                "infowindow": null
                            },
                            "fieldLocationType": null,
                            "fieldSchoolLocation": null,
                            "paraType": "school_location"
                        },
                        "373036": {
                            "fieldAddress": "Kreenholmi tn 45, Narva linn, Ida-Viru maakond",
                            "fieldCoordinates": {
                                "name": "Kreenholmi tn 45, Narva linn, Ida-Viru maakond",
                                "lat": "59.360678",
                                "lon": "28.188351",
                                "zoom": null,
                                "type": null,
                                "width": null,
                                "height": null,
                                "marker": null,
                                "traffic": null,
                                "marker_icon": null,
                                "controls": null,
                                "infowindow": null
                            },
                            "fieldLocationType": null,
                            "fieldSchoolLocation": null,
                            "paraType": "school_location"
                        }
                    },
                    "fieldSchoolWebpageAddress": "https://kutsehariduskeskus.ee/",
                    "fieldSpecialClass": null,
                    "fieldTeachingLanguage": {
                        "1689": "eesti keel",
                        "1691": "vene keel"
                    },
                    "uid": "1",
                    "title": "Ida-Virumaa Kutsehariduskeskus",
                    "created": "1538404211"
                }
            },
            "fieldIscedfBoard": {
                "2525": "Informatsiooni- ja kommunikatsioonitehnoloogiad"
            },
            "fieldIscedfDetailed": {
                "2529": "Andmebaaside ja võrgu disain ning haldus"
            },
            "fieldIscedfNarrow": {
                "2526": "Informatsiooni- ja kommunikatsioonitehnoloogiad"
            },
            "fieldMetatags": null,
            "fieldMinimumRequiredEducation": null,
            "fieldPracticalTrainingAmount": "30",
            "fieldSchoolAddress": "Tallinna mnt 13, Sillamäe linn, Ida-Viru maakond",
            "fieldSchoolSearchAddress": "Sillamäe linn, Ida-Viru maakond",
            "fieldSchoolWebsite": "https://kutsehariduskeskus.ee/",
            "fieldShortDescription": null,
            "fieldSpecialization": "määramata",
            "fieldStudyProgrammeLevel": {
                "2373": "Kutseõpe põhihariduse baasil"
            },
            "fieldStudyProgrammeType": {
                "644": "Kutsehariduse õppekava"
            },
            "fieldTeachingLanguage": {
                "1689": "eesti keel",
                "1691": "vene keel"
            },
            "uid": "1",
            "title": "IT-süsteemide nooremspetsialist",
            "created": "1537777045"
        },
        {
            "nid": "8167",
            "path": "/erialad/tisler-9",
            "id": "studyProgramme",
            "fieldAccreditationStatus": null,
            "fieldAccreditationValidUntil": null,
            "fieldAdmissionBeginDate": null,
            "fieldAdmissionEndDate": null,
            "fieldAdmissionId": null,
            "fieldAdmissionLink": null,
            "fieldAmount": "120",
            "fieldAmountUnit": "EKAP",
            "fieldDegreeOrDiplomaAwarded": null,
            "fieldDuration": "24",
            "fieldEducationalInstitution": {
                "9641": {
                    "fieldEducationalInstitutionTy": {
                        "2364": "Kutseõppeasutus"
                    },
                    "fieldOwnershipType": {
                        "2033": "Riigiomandus"
                    },
                    "fieldSchoolContactEmail": "ehituskool@ehituskool.ee",
                    "fieldSchoolContactPhone": "6519040",
                    "fieldSchoolLocation": {
                        "7219": {
                            "fieldAddress": "Pärnu mnt 162/1, Kesklinna linnaosa, Tallinn, Harju maakond",
                            "fieldCoordinates": {
                                "name": "Pärnu mnt 162/1, Kesklinna linnaosa, Tallinn, Harju maakond",
                                "lat": "59.40398",
                                "lon": "24.729784",
                                "zoom": null,
                                "type": null,
                                "width": null,
                                "height": null,
                                "marker": null,
                                "traffic": null,
                                "marker_icon": null,
                                "controls": null,
                                "infowindow": null
                            },
                            "fieldLocationType": "L",
                            "fieldSchoolLocation": {
                                "73": "Kesklinna linnaosa"
                            },
                            "paraType": "school_location"
                        }
                    },
                    "fieldSchoolWebpageAddress": "http://www.ehituskool.ee",
                    "fieldSpecialClass": null,
                    "fieldTeachingLanguage": {
                        "1689": "eesti keel",
                        "1691": "vene keel"
                    },
                    "uid": "1",
                    "title": "Tallinna Ehituskool",
                    "created": "1538403865"
                }
            },
            "fieldIscedfBoard": {
                "2538": "Tehnika, tootmine ja ehitus"
            },
            "fieldIscedfDetailed": {
                "2557": "Materjalide töötlemine (klaas, paber, plast ja puit)"
            },
            "fieldIscedfNarrow": {
                "2554": "Tootmine ja töötlemine"
            },
            "fieldMetatags": null,
            "fieldMinimumRequiredEducation": null,
            "fieldPracticalTrainingAmount": "30",
            "fieldSchoolAddress": "Pärnu mnt 162/1, Kesklinna linnaosa, Tallinn, Harju maakond",
            "fieldSchoolSearchAddress": "Kesklinna linnaosa, Tallinn, Harju maakond",
            "fieldSchoolWebsite": "http://www.ehituskool.ee",
            "fieldShortDescription": null,
            "fieldSpecialization": "määramata",
            "fieldStudyProgrammeLevel": {
                "2373": "Kutseõpe põhihariduse baasil"
            },
            "fieldStudyProgrammeType": {
                "644": "Kutsehariduse õppekava"
            },
            "fieldTeachingLanguage": {
                "1689": "eesti keel",
                "1691": "vene keel"
            },
            "uid": "1",
            "title": "Tisler",
            "created": "1537777049"
        },
        {
            "nid": "8206",
            "path": "/erialad/soojuspumpade-paigaldaja",
            "id": "studyProgramme",
            "fieldAccreditationStatus": null,
            "fieldAccreditationValidUntil": null,
            "fieldAdmissionBeginDate": null,
            "fieldAdmissionEndDate": null,
            "fieldAdmissionId": null,
            "fieldAdmissionLink": null,
            "fieldAmount": "30",
            "fieldAmountUnit": "EKAP",
            "fieldDegreeOrDiplomaAwarded": null,
            "fieldDuration": "12",
            "fieldEducationalInstitution": {
                "9641": {
                    "fieldEducationalInstitutionTy": {
                        "2364": "Kutseõppeasutus"
                    },
                    "fieldOwnershipType": {
                        "2033": "Riigiomandus"
                    },
                    "fieldSchoolContactEmail": "ehituskool@ehituskool.ee",
                    "fieldSchoolContactPhone": "6519040",
                    "fieldSchoolLocation": {
                        "7219": {
                            "fieldAddress": "Pärnu mnt 162/1, Kesklinna linnaosa, Tallinn, Harju maakond",
                            "fieldCoordinates": {
                                "name": "Pärnu mnt 162/1, Kesklinna linnaosa, Tallinn, Harju maakond",
                                "lat": "59.40398",
                                "lon": "24.729784",
                                "zoom": null,
                                "type": null,
                                "width": null,
                                "height": null,
                                "marker": null,
                                "traffic": null,
                                "marker_icon": null,
                                "controls": null,
                                "infowindow": null
                            },
                            "fieldLocationType": "L",
                            "fieldSchoolLocation": {
                                "73": "Kesklinna linnaosa"
                            },
                            "paraType": "school_location"
                        }
                    },
                    "fieldSchoolWebpageAddress": "http://www.ehituskool.ee",
                    "fieldSpecialClass": null,
                    "fieldTeachingLanguage": {
                        "1689": "eesti keel",
                        "1691": "vene keel"
                    },
                    "uid": "1",
                    "title": "Tallinna Ehituskool",
                    "created": "1538403865"
                }
            },
            "fieldIscedfBoard": {
                "2538": "Tehnika, tootmine ja ehitus"
            },
            "fieldIscedfDetailed": {
                "2568": "Ehitus ja tsiviilrajatised"
            },
            "fieldIscedfNarrow": {
                "2565": "Arhitektuur ja ehitus"
            },
            "fieldMetatags": null,
            "fieldMinimumRequiredEducation": null,
            "fieldPracticalTrainingAmount": "15",
            "fieldSchoolAddress": "Pärnu mnt 162/1, Kesklinna linnaosa, Tallinn, Harju maakond",
            "fieldSchoolSearchAddress": "Kesklinna linnaosa, Tallinn, Harju maakond",
            "fieldSchoolWebsite": "http://www.ehituskool.ee",
            "fieldShortDescription": null,
            "fieldSpecialization": "määramata",
            "fieldStudyProgrammeLevel": {
                "2373": "Kutseõpe põhihariduse baasil"
            },
            "fieldStudyProgrammeType": {
                "644": "Kutsehariduse õppekava"
            },
            "fieldTeachingLanguage": {
                "1689": "eesti keel"
            },
            "uid": "1",
            "title": "Soojuspumpade paigaldaja",
            "created": "1537777051"
        },
        {
            "nid": "8327",
            "path": "/erialad/turundusspetsialist",
            "id": "studyProgramme",
            "fieldAccreditationStatus": null,
            "fieldAccreditationValidUntil": null,
            "fieldAdmissionBeginDate": null,
            "fieldAdmissionEndDate": null,
            "fieldAdmissionId": null,
            "fieldAdmissionLink": null,
            "fieldAmount": "150",
            "fieldAmountUnit": "EKAP",
            "fieldDegreeOrDiplomaAwarded": null,
            "fieldDuration": "30",
            "fieldEducationalInstitution": {
                "9251": {
                    "fieldEducationalInstitutionTy": {
                        "2364": "Kutseõppeasutus"
                    },
                    "fieldOwnershipType": {
                        "2033": "Riigiomandus"
                    },
                    "fieldSchoolContactEmail": "info@tmk.edu.ee",
                    "fieldSchoolContactPhone": "56281688",
                    "fieldSchoolLocation": {
                        "6831": {
                            "fieldAddress": "A. H. Tammsaare tee 147, Mustamäe linnaosa, Tallinn, Harju maakond",
                            "fieldCoordinates": {
                                "name": "A. H. Tammsaare tee 147, Mustamäe linnaosa, Tallinn, Harju maakond",
                                "lat": "59.409662",
                                "lon": "24.67088",
                                "zoom": null,
                                "type": null,
                                "width": null,
                                "height": null,
                                "marker": null,
                                "traffic": null,
                                "marker_icon": null,
                                "controls": null,
                                "infowindow": null
                            },
                            "fieldLocationType": "L",
                            "fieldSchoolLocation": {
                                "70": "Mustamäe linnaosa"
                            },
                            "paraType": "school_location"
                        }
                    },
                    "fieldSchoolWebpageAddress": "http://www.tmk.edu.ee",
                    "fieldSpecialClass": null,
                    "fieldTeachingLanguage": {
                        "1689": "eesti keel",
                        "1691": "vene keel"
                    },
                    "uid": "1",
                    "title": "Tallinna Majanduskool",
                    "created": "1538403795"
                }
            },
            "fieldIscedfBoard": {
                "2463": "Ärindus, haldus ja õigus"
            },
            "fieldIscedfDetailed": {
                "2471": "Turundus ja reklaam"
            },
            "fieldIscedfNarrow": {
                "2464": "Ärindus ja haldus"
            },
            "fieldMetatags": null,
            "fieldMinimumRequiredEducation": null,
            "fieldPracticalTrainingAmount": "38",
            "fieldSchoolAddress": "A. H. Tammsaare tee 147, Mustamäe linnaosa, Tallinn, Harju maakond",
            "fieldSchoolSearchAddress": "Mustamäe linnaosa, Tallinn, Harju maakond",
            "fieldSchoolWebsite": "http://www.tmk.edu.ee",
            "fieldShortDescription": null,
            "fieldSpecialization": "määramata",
            "fieldStudyProgrammeLevel": {
                "2013": "Kutseõpe keskhariduse baasil"
            },
            "fieldStudyProgrammeType": {
                "644": "Kutsehariduse õppekava"
            },
            "fieldTeachingLanguage": {
                "1689": "eesti keel"
            },
            "uid": "1",
            "title": "Turundusspetsialist",
            "created": "1537777061"
        },
        {
            "nid": "8328",
            "path": "/erialad/sotsiaalmeedia-spetsialist",
            "id": "studyProgramme",
            "fieldAccreditationStatus": null,
            "fieldAccreditationValidUntil": null,
            "fieldAdmissionBeginDate": null,
            "fieldAdmissionEndDate": null,
            "fieldAdmissionId": null,
            "fieldAdmissionLink": null,
            "fieldAmount": "120",
            "fieldAmountUnit": "EKAP",
            "fieldDegreeOrDiplomaAwarded": null,
            "fieldDuration": "24",
            "fieldEducationalInstitution": {
                "9251": {
                    "fieldEducationalInstitutionTy": {
                        "2364": "Kutseõppeasutus"
                    },
                    "fieldOwnershipType": {
                        "2033": "Riigiomandus"
                    },
                    "fieldSchoolContactEmail": "info@tmk.edu.ee",
                    "fieldSchoolContactPhone": "56281688",
                    "fieldSchoolLocation": {
                        "6831": {
                            "fieldAddress": "A. H. Tammsaare tee 147, Mustamäe linnaosa, Tallinn, Harju maakond",
                            "fieldCoordinates": {
                                "name": "A. H. Tammsaare tee 147, Mustamäe linnaosa, Tallinn, Harju maakond",
                                "lat": "59.409662",
                                "lon": "24.67088",
                                "zoom": null,
                                "type": null,
                                "width": null,
                                "height": null,
                                "marker": null,
                                "traffic": null,
                                "marker_icon": null,
                                "controls": null,
                                "infowindow": null
                            },
                            "fieldLocationType": "L",
                            "fieldSchoolLocation": {
                                "70": "Mustamäe linnaosa"
                            },
                            "paraType": "school_location"
                        }
                    },
                    "fieldSchoolWebpageAddress": "http://www.tmk.edu.ee",
                    "fieldSpecialClass": null,
                    "fieldTeachingLanguage": {
                        "1689": "eesti keel",
                        "1691": "vene keel"
                    },
                    "uid": "1",
                    "title": "Tallinna Majanduskool",
                    "created": "1538403795"
                }
            },
            "fieldIscedfBoard": {
                "2463": "Ärindus, haldus ja õigus"
            },
            "fieldIscedfDetailed": {
                "2471": "Turundus ja reklaam"
            },
            "fieldIscedfNarrow": {
                "2464": "Ärindus ja haldus"
            },
            "fieldMetatags": null,
            "fieldMinimumRequiredEducation": null,
            "fieldPracticalTrainingAmount": "36",
            "fieldSchoolAddress": "A. H. Tammsaare tee 147, Mustamäe linnaosa, Tallinn, Harju maakond",
            "fieldSchoolSearchAddress": "Mustamäe linnaosa, Tallinn, Harju maakond",
            "fieldSchoolWebsite": "http://www.tmk.edu.ee",
            "fieldShortDescription": null,
            "fieldSpecialization": "määramata",
            "fieldStudyProgrammeLevel": {
                "2013": "Kutseõpe keskhariduse baasil"
            },
            "fieldStudyProgrammeType": {
                "644": "Kutsehariduse õppekava"
            },
            "fieldTeachingLanguage": {
                "1689": "eesti keel"
            },
            "uid": "1",
            "title": "Sotsiaalmeedia spetsialist",
            "created": "1537777061"
        },
        {
            "nid": "8339",
            "path": "/erialad/kondiiter-1",
            "id": "studyProgramme",
            "fieldAccreditationStatus": null,
            "fieldAccreditationValidUntil": null,
            "fieldAdmissionBeginDate": null,
            "fieldAdmissionEndDate": null,
            "fieldAdmissionId": null,
            "fieldAdmissionLink": null,
            "fieldAmount": "90",
            "fieldAmountUnit": "EKAP",
            "fieldDegreeOrDiplomaAwarded": null,
            "fieldDuration": "18",
            "fieldEducationalInstitution": {
                "11411": {
                    "fieldEducationalInstitutionTy": {
                        "2364": "Kutseõppeasutus"
                    },
                    "fieldOwnershipType": {
                        "1688": "Munitsipaal"
                    },
                    "fieldSchoolContactEmail": "info@voco.ee",
                    "fieldSchoolContactPhone": "7361866",
                    "fieldSchoolLocation": {
                        "8984": {
                            "fieldAddress": "Kopli tn 1, Tartu linn, Tartu linn, Tartu maakond",
                            "fieldCoordinates": {
                                "name": "Kopli tn 1, Tartu linn, Tartu linn, Tartu maakond",
                                "lat": "58.3494",
                                "lon": "26.714176",
                                "zoom": null,
                                "type": null,
                                "width": null,
                                "height": null,
                                "marker": null,
                                "traffic": null,
                                "marker_icon": null,
                                "controls": null,
                                "infowindow": null
                            },
                            "fieldLocationType": "L",
                            "fieldSchoolLocation": {
                                "494": "Tartu linn"
                            },
                            "paraType": "school_location"
                        }
                    },
                    "fieldSchoolWebpageAddress": "https://voco.ee",
                    "fieldSpecialClass": null,
                    "fieldTeachingLanguage": {
                        "1689": "eesti keel",
                        "1691": "vene keel"
                    },
                    "uid": "1",
                    "title": "Tartu Rakenduslik Kolledž",
                    "created": "1538404224"
                }
            },
            "fieldIscedfBoard": {
                "2538": "Tehnika, tootmine ja ehitus"
            },
            "fieldIscedfDetailed": {
                "2555": "Toiduainete töötlemine"
            },
            "fieldIscedfNarrow": {
                "2554": "Tootmine ja töötlemine"
            },
            "fieldMetatags": null,
            "fieldMinimumRequiredEducation": null,
            "fieldPracticalTrainingAmount": "23",
            "fieldSchoolAddress": "Kopli tn 1, Tartu linn, Tartu linn, Tartu maakond",
            "fieldSchoolSearchAddress": "Tartu linn, Tartu linn, Tartu maakond",
            "fieldSchoolWebsite": "https://voco.ee",
            "fieldShortDescription": null,
            "fieldSpecialization": "määramata",
            "fieldStudyProgrammeLevel": {
                "2373": "Kutseõpe põhihariduse baasil"
            },
            "fieldStudyProgrammeType": {
                "644": "Kutsehariduse õppekava"
            },
            "fieldTeachingLanguage": {
                "1689": "eesti keel"
            },
            "uid": "1",
            "title": "Kondiiter",
            "created": "1537777062"
        },
        {
            "nid": "8341",
            "path": "/erialad/kondiiter-3",
            "id": "studyProgramme",
            "fieldAccreditationStatus": null,
            "fieldAccreditationValidUntil": null,
            "fieldAdmissionBeginDate": "1730412000",
            "fieldAdmissionEndDate": "1734012014",
            "fieldAdmissionId": "14901",
            "fieldAdmissionLink": "https://sais.ee/AdmissionSearch/View/14901",
            "fieldAmount": "60",
            "fieldAmountUnit": "EKAP",
            "fieldDegreeOrDiplomaAwarded": null,
            "fieldDuration": "12",
            "fieldEducationalInstitution": {
                "10947": {
                    "fieldEducationalInstitutionTy": {
                        "2364": "Kutseõppeasutus"
                    },
                    "fieldOwnershipType": {
                        "2033": "Riigiomandus"
                    },
                    "fieldSchoolContactEmail": "kool@olustvere.edu.ee",
                    "fieldSchoolContactPhone": "4374290",
                    "fieldSchoolLocation": {
                        "8522": {
                            "fieldAddress": "Müüri tn 4, Olustvere alevik, Põhja-Sakala vald, Viljandi maakond",
                            "fieldCoordinates": {
                                "name": "Müüri tn 4, Olustvere alevik, Põhja-Sakala vald, Viljandi maakond",
                                "lat": "58.5556",
                                "lon": "25.56782",
                                "zoom": null,
                                "type": null,
                                "width": null,
                                "height": null,
                                "marker": null,
                                "traffic": null,
                                "marker_icon": null,
                                "controls": null,
                                "infowindow": null
                            },
                            "fieldLocationType": "L",
                            "fieldSchoolLocation": {
                                "372": "Olustvere alevik"
                            },
                            "paraType": "school_location"
                        }
                    },
                    "fieldSchoolWebpageAddress": "http://www.olustvere.edu.ee",
                    "fieldSpecialClass": null,
                    "fieldTeachingLanguage": {
                        "1689": "eesti keel"
                    },
                    "uid": "1",
                    "title": "Olustvere Teenindus- ja Maamajanduskool",
                    "created": "1538404134"
                }
            },
            "fieldIscedfBoard": {
                "2538": "Tehnika, tootmine ja ehitus"
            },
            "fieldIscedfDetailed": {
                "2555": "Toiduainete töötlemine"
            },
            "fieldIscedfNarrow": {
                "2554": "Tootmine ja töötlemine"
            },
            "fieldMetatags": null,
            "fieldMinimumRequiredEducation": {
                "3225": "põhiharidus (210)"
            },
            "fieldPracticalTrainingAmount": "15",
            "fieldSchoolAddress": "Müüri tn 4, Olustvere alevik, Põhja-Sakala vald, Viljandi maakond",
            "fieldSchoolSearchAddress": "Olustvere alevik, Põhja-Sakala vald, Viljandi maakond",
            "fieldSchoolWebsite": "http://www.olustvere.edu.ee",
            "fieldShortDescription": null,
            "fieldSpecialization": "määramata",
            "fieldStudyProgrammeLevel": {
                "2373": "Kutseõpe põhihariduse baasil"
            },
            "fieldStudyProgrammeType": {
                "644": "Kutsehariduse õppekava"
            },
            "fieldTeachingLanguage": {
                "1689": "eesti keel"
            },
            "uid": "1",
            "title": "Kondiiter",
            "created": "1537777062"
        },
        {
            "nid": "8361",
            "path": "/erialad/pagar",
            "id": "studyProgramme",
            "fieldAccreditationStatus": null,
            "fieldAccreditationValidUntil": null,
            "fieldAdmissionBeginDate": null,
            "fieldAdmissionEndDate": null,
            "fieldAdmissionId": null,
            "fieldAdmissionLink": null,
            "fieldAmount": "60",
            "fieldAmountUnit": "EKAP",
            "fieldDegreeOrDiplomaAwarded": null,
            "fieldDuration": "12",
            "fieldEducationalInstitution": {
                "11411": {
                    "fieldEducationalInstitutionTy": {
                        "2364": "Kutseõppeasutus"
                    },
                    "fieldOwnershipType": {
                        "1688": "Munitsipaal"
                    },
                    "fieldSchoolContactEmail": "info@voco.ee",
                    "fieldSchoolContactPhone": "7361866",
                    "fieldSchoolLocation": {
                        "8984": {
                            "fieldAddress": "Kopli tn 1, Tartu linn, Tartu linn, Tartu maakond",
                            "fieldCoordinates": {
                                "name": "Kopli tn 1, Tartu linn, Tartu linn, Tartu maakond",
                                "lat": "58.3494",
                                "lon": "26.714176",
                                "zoom": null,
                                "type": null,
                                "width": null,
                                "height": null,
                                "marker": null,
                                "traffic": null,
                                "marker_icon": null,
                                "controls": null,
                                "infowindow": null
                            },
                            "fieldLocationType": "L",
                            "fieldSchoolLocation": {
                                "494": "Tartu linn"
                            },
                            "paraType": "school_location"
                        }
                    },
                    "fieldSchoolWebpageAddress": "https://voco.ee",
                    "fieldSpecialClass": null,
                    "fieldTeachingLanguage": {
                        "1689": "eesti keel",
                        "1691": "vene keel"
                    },
                    "uid": "1",
                    "title": "Tartu Rakenduslik Kolledž",
                    "created": "1538404224"
                }
            },
            "fieldIscedfBoard": {
                "2538": "Tehnika, tootmine ja ehitus"
            },
            "fieldIscedfDetailed": {
                "2555": "Toiduainete töötlemine"
            },
            "fieldIscedfNarrow": {
                "2554": "Tootmine ja töötlemine"
            },
            "fieldMetatags": null,
            "fieldMinimumRequiredEducation": null,
            "fieldPracticalTrainingAmount": "15",
            "fieldSchoolAddress": "Kopli tn 1, Tartu linn, Tartu linn, Tartu maakond",
            "fieldSchoolSearchAddress": "Tartu linn, Tartu linn, Tartu maakond",
            "fieldSchoolWebsite": "https://voco.ee",
            "fieldShortDescription": null,
            "fieldSpecialization": "määramata",
            "fieldStudyProgrammeLevel": {
                "2373": "Kutseõpe põhihariduse baasil"
            },
            "fieldStudyProgrammeType": {
                "644": "Kutsehariduse õppekava"
            },
            "fieldTeachingLanguage": {
                "1689": "eesti keel"
            },
            "uid": "1",
            "title": "Pagar",
            "created": "1537777063"
        }
    ],
    "count": 3876,
    "field_neurotolge_state": "translated_with_neurotolge"
}