{
    "entities": [
        {
            "nid": "7392",
            "path": "/erialad/plaatija",
            "id": "studyProgramme",
            "fieldAccreditationStatus": null,
            "fieldAccreditationValidUntil": null,
            "fieldAdmissionBeginDate": "1764626400",
            "fieldAdmissionEndDate": "1765835940",
            "fieldAdmissionId": "18446",
            "fieldAdmissionLink": "https://sais.ee/AdmissionSearch/View/18446",
            "fieldAmount": "30",
            "fieldAmountUnit": "EKAP",
            "fieldDegreeOrDiplomaAwarded": null,
            "fieldDuration": "6",
            "fieldEducationalInstitution": {
                "11825": {
                    "fieldEducationalInstitutionTy": {
                        "1686": "Gümnaasium",
                        "2364": "Kutseõppeasutus",
                        "2371": "Põhikool"
                    },
                    "fieldOwnershipType": {
                        "2033": "Riigiomandus"
                    },
                    "fieldSchoolContactEmail": "ewers@ewers.ee",
                    "fieldSchoolContactPhone": "7850800",
                    "fieldSchoolLocation": {
                        "9398": {
                            "fieldAddress": "Kooli tee 1, Väimela alevik, Võru vald, Võru maakond",
                            "fieldCoordinates": {
                                "name": "Kooli tee 1, Väimela alevik, Võru vald, Võru maakond",
                                "lat": "57.891173",
                                "lon": "27.013394",
                                "zoom": null,
                                "type": null,
                                "width": null,
                                "height": null,
                                "marker": null,
                                "traffic": null,
                                "marker_icon": null,
                                "controls": null,
                                "infowindow": null
                            },
                            "fieldLocationType": "L",
                            "fieldSchoolLocation": {
                                "590": "Väimela alevik"
                            },
                            "paraType": "school_location"
                        }
                    },
                    "fieldSchoolWebpageAddress": "http://www.ewers.ee",
                    "fieldSpecialClass": null,
                    "fieldTeachingLanguage": {
                        "1689": "eesti keel"
                    },
                    "uid": "1",
                    "title": "Võrumaa Haridus- ja Tehnoloogiakeskus",
                    "created": "1538404301"
                }
            },
            "fieldIscedfBoard": {
                "2538": "Tehnika, tootmine ja ehitus"
            },
            "fieldIscedfDetailed": {
                "2568": "Ehitus ja tsiviilrajatised"
            },
            "fieldIscedfNarrow": {
                "2565": "Arhitektuur ja ehitus"
            },
            "fieldMetatags": null,
            "fieldMinimumRequiredEducation": {
                "3225": "põhiharidus (210)"
            },
            "fieldPracticalTrainingAmount": "7",
            "fieldSchoolAddress": "Kooli tee 1, Väimela alevik, Võru vald, Võru maakond",
            "fieldSchoolSearchAddress": "Väimela alevik, Võru vald, Võru maakond",
            "fieldSchoolWebsite": "http://www.ewers.ee",
            "fieldShortDescription": null,
            "fieldSpecialization": "Plaatija",
            "fieldStudyProgrammeLevel": {
                "2373": "Kutseõpe põhihariduse baasil"
            },
            "fieldStudyProgrammeType": {
                "644": "Kutsehariduse õppekava"
            },
            "fieldTeachingLanguage": {
                "1689": "eesti keel"
            },
            "uid": "1",
            "title": "Plaatija",
            "created": "1537776993"
        },
        {
            "nid": "7562",
            "path": "/erialad/puhastust%C3%B6%C3%B6de-juht-0",
            "id": "studyProgramme",
            "fieldAccreditationStatus": null,
            "fieldAccreditationValidUntil": null,
            "fieldAdmissionBeginDate": "1755464400",
            "fieldAdmissionEndDate": "1768082400",
            "fieldAdmissionId": "16884",
            "fieldAdmissionLink": "https://sais.ee/AdmissionSearch/View/16884",
            "fieldAmount": "30",
            "fieldAmountUnit": "EKAP",
            "fieldDegreeOrDiplomaAwarded": null,
            "fieldDuration": "6",
            "fieldEducationalInstitution": {
                "10890": {
                    "fieldEducationalInstitutionTy": {
                        "1686": "Gümnaasium",
                        "2364": "Kutseõppeasutus",
                        "2371": "Põhikool"
                    },
                    "fieldOwnershipType": {
                        "2033": "Riigiomandus"
                    },
                    "fieldSchoolContactEmail": "kool@jkhk.ee",
                    "fieldSchoolContactPhone": "5253736 ",
                    "fieldSchoolLocation": {
                        "8465": {
                            "fieldAddress": "Tallinna tn 46, Paide linn, Paide linn, Järva maakond",
                            "fieldCoordinates": {
                                "name": "Tallinna tn 46, Paide linn, Paide linn, Järva maakond",
                                "lat": "58.891855",
                                "lon": "25.567184",
                                "zoom": null,
                                "type": null,
                                "width": null,
                                "height": null,
                                "marker": null,
                                "traffic": null,
                                "marker_icon": null,
                                "controls": null,
                                "infowindow": null
                            },
                            "fieldLocationType": "L",
                            "fieldSchoolLocation": {
                                "344": "Paide linn"
                            },
                            "paraType": "school_location"
                        },
                        "373039": {
                            "fieldAddress": "Tehnikumi tn 4, Särevere alevik, Türi vald, Järva maakond",
                            "fieldCoordinates": {
                                "name": "Tehnikumi tn 4, Särevere alevik, Türi vald, Järva maakond",
                                "lat": "58.782417",
                                "lon": "25.432146",
                                "zoom": null,
                                "type": null,
                                "width": null,
                                "height": null,
                                "marker": null,
                                "traffic": null,
                                "marker_icon": null,
                                "controls": null,
                                "infowindow": null
                            },
                            "fieldLocationType": null,
                            "fieldSchoolLocation": null,
                            "paraType": "school_location"
                        }
                    },
                    "fieldSchoolWebpageAddress": "http://jkhk.ee",
                    "fieldSpecialClass": null,
                    "fieldTeachingLanguage": {
                        "1689": "eesti keel"
                    },
                    "uid": "1",
                    "title": "Järvamaa Kutsehariduskeskus",
                    "created": "1538404121"
                }
            },
            "fieldIscedfBoard": {
                "2632": "Teenindus"
            },
            "fieldIscedfDetailed": {
                "2634": "Koduteenindus"
            },
            "fieldIscedfNarrow": {
                "2633": "Isikuteenindus"
            },
            "fieldMetatags": null,
            "fieldMinimumRequiredEducation": {
                "3226": "üldkeskharidus (310)"
            },
            "fieldPracticalTrainingAmount": "8",
            "fieldSchoolAddress": "Tallinna tn 46, Paide linn, Paide linn, Järva maakond",
            "fieldSchoolSearchAddress": "Paide linn, Paide linn, Järva maakond",
            "fieldSchoolWebsite": "http://jkhk.ee",
            "fieldShortDescription": null,
            "fieldSpecialization": "määramata",
            "fieldStudyProgrammeLevel": {
                "2013": "Kutseõpe keskhariduse baasil"
            },
            "fieldStudyProgrammeType": {
                "644": "Kutsehariduse õppekava"
            },
            "fieldTeachingLanguage": {
                "1689": "eesti keel"
            },
            "uid": "1",
            "title": "Puhastustööde juht",
            "created": "1537777005"
        },
        {
            "nid": "14353",
            "path": "/erialad/kujundusgraafik-0",
            "id": "studyProgramme",
            "fieldAccreditationStatus": null,
            "fieldAccreditationValidUntil": null,
            "fieldAdmissionBeginDate": "1762812000",
            "fieldAdmissionEndDate": "1768168740",
            "fieldAdmissionId": "18407",
            "fieldAdmissionLink": "https://sais.ee/AdmissionSearch/View/18407",
            "fieldAmount": "60",
            "fieldAmountUnit": "EKAP",
            "fieldDegreeOrDiplomaAwarded": null,
            "fieldDuration": "12",
            "fieldEducationalInstitution": {
                "11345": {
                    "fieldEducationalInstitutionTy": {
                        "2364": "Kutseõppeasutus"
                    },
                    "fieldOwnershipType": {
                        "2033": "Riigiomandus"
                    },
                    "fieldSchoolContactEmail": "info@ivkhk.ee",
                    "fieldSchoolContactPhone": "3320381",
                    "fieldSchoolLocation": {
                        "8918": {
                            "fieldAddress": "Tallinna mnt 13, Sillamäe linn, Ida-Viru maakond",
                            "fieldCoordinates": {
                                "name": "Tallinna mnt 13, Sillamäe linn, Ida-Viru maakond",
                                "lat": "59.39098",
                                "lon": "27.793492",
                                "zoom": null,
                                "type": null,
                                "width": null,
                                "height": null,
                                "marker": null,
                                "traffic": null,
                                "marker_icon": null,
                                "controls": null,
                                "infowindow": null
                            },
                            "fieldLocationType": "L",
                            "fieldSchoolLocation": {
                                "485": "Sillamäe linn"
                            },
                            "paraType": "school_location"
                        },
                        "373035": {
                            "fieldAddress": "Kutse tn 13, Jõhvi linn, Jõhvi vald, Ida-Viru maakond",
                            "fieldCoordinates": {
                                "name": "Kutse tn 13, Jõhvi linn, Jõhvi vald, Ida-Viru maakond",
                                "lat": "59.360033",
                                "lon": "27.399148",
                                "zoom": null,
                                "type": null,
                                "width": null,
                                "height": null,
                                "marker": null,
                                "traffic": null,
                                "marker_icon": null,
                                "controls": null,
                                "infowindow": null
                            },
                            "fieldLocationType": null,
                            "fieldSchoolLocation": null,
                            "paraType": "school_location"
                        },
                        "373036": {
                            "fieldAddress": "Kreenholmi tn 45, Narva linn, Ida-Viru maakond",
                            "fieldCoordinates": {
                                "name": "Kreenholmi tn 45, Narva linn, Ida-Viru maakond",
                                "lat": "59.360678",
                                "lon": "28.188351",
                                "zoom": null,
                                "type": null,
                                "width": null,
                                "height": null,
                                "marker": null,
                                "traffic": null,
                                "marker_icon": null,
                                "controls": null,
                                "infowindow": null
                            },
                            "fieldLocationType": null,
                            "fieldSchoolLocation": null,
                            "paraType": "school_location"
                        }
                    },
                    "fieldSchoolWebpageAddress": "https://kutsehariduskeskus.ee/",
                    "fieldSpecialClass": null,
                    "fieldTeachingLanguage": {
                        "1689": "eesti keel",
                        "1691": "vene keel"
                    },
                    "uid": "1",
                    "title": "Ida-Virumaa Kutsehariduskeskus",
                    "created": "1538404211"
                }
            },
            "fieldIscedfBoard": {
                "2402": "Humanitaaria ja kunstid"
            },
            "fieldIscedfDetailed": {
                "2404": "Audiovisuaalsed tehnikad ja meedia tootmine"
            },
            "fieldIscedfNarrow": {
                "2403": "Kunstid"
            },
            "fieldMetatags": null,
            "fieldMinimumRequiredEducation": {
                "3226": "üldkeskharidus (310)"
            },
            "fieldPracticalTrainingAmount": "15",
            "fieldSchoolAddress": "Tallinna mnt 13, Sillamäe linn, Ida-Viru maakond",
            "fieldSchoolSearchAddress": "Sillamäe linn, Ida-Viru maakond",
            "fieldSchoolWebsite": "https://kutsehariduskeskus.ee/",
            "fieldShortDescription": null,
            "fieldSpecialization": "Kujundusgraafik",
            "fieldStudyProgrammeLevel": {
                "2013": "Kutseõpe keskhariduse baasil"
            },
            "fieldStudyProgrammeType": {
                "644": "Kutsehariduse õppekava"
            },
            "fieldTeachingLanguage": {
                "1689": "eesti keel",
                "1691": "vene keel"
            },
            "uid": "1",
            "title": "Kujundusgraafik",
            "created": "1619478480"
        },
        {
            "nid": "15255289",
            "path": "/erialad/krohvija-4",
            "id": "studyProgramme",
            "fieldAccreditationStatus": null,
            "fieldAccreditationValidUntil": null,
            "fieldAdmissionBeginDate": "1762812000",
            "fieldAdmissionEndDate": "1768168740",
            "fieldAdmissionId": "18398",
            "fieldAdmissionLink": "https://sais.ee/AdmissionSearch/View/18398",
            "fieldAmount": "60",
            "fieldAmountUnit": "EKAP",
            "fieldDegreeOrDiplomaAwarded": null,
            "fieldDuration": "12",
            "fieldEducationalInstitution": {
                "11345": {
                    "fieldEducationalInstitutionTy": {
                        "2364": "Kutseõppeasutus"
                    },
                    "fieldOwnershipType": {
                        "2033": "Riigiomandus"
                    },
                    "fieldSchoolContactEmail": "info@ivkhk.ee",
                    "fieldSchoolContactPhone": "3320381",
                    "fieldSchoolLocation": {
                        "8918": {
                            "fieldAddress": "Tallinna mnt 13, Sillamäe linn, Ida-Viru maakond",
                            "fieldCoordinates": {
                                "name": "Tallinna mnt 13, Sillamäe linn, Ida-Viru maakond",
                                "lat": "59.39098",
                                "lon": "27.793492",
                                "zoom": null,
                                "type": null,
                                "width": null,
                                "height": null,
                                "marker": null,
                                "traffic": null,
                                "marker_icon": null,
                                "controls": null,
                                "infowindow": null
                            },
                            "fieldLocationType": "L",
                            "fieldSchoolLocation": {
                                "485": "Sillamäe linn"
                            },
                            "paraType": "school_location"
                        },
                        "373035": {
                            "fieldAddress": "Kutse tn 13, Jõhvi linn, Jõhvi vald, Ida-Viru maakond",
                            "fieldCoordinates": {
                                "name": "Kutse tn 13, Jõhvi linn, Jõhvi vald, Ida-Viru maakond",
                                "lat": "59.360033",
                                "lon": "27.399148",
                                "zoom": null,
                                "type": null,
                                "width": null,
                                "height": null,
                                "marker": null,
                                "traffic": null,
                                "marker_icon": null,
                                "controls": null,
                                "infowindow": null
                            },
                            "fieldLocationType": null,
                            "fieldSchoolLocation": null,
                            "paraType": "school_location"
                        },
                        "373036": {
                            "fieldAddress": "Kreenholmi tn 45, Narva linn, Ida-Viru maakond",
                            "fieldCoordinates": {
                                "name": "Kreenholmi tn 45, Narva linn, Ida-Viru maakond",
                                "lat": "59.360678",
                                "lon": "28.188351",
                                "zoom": null,
                                "type": null,
                                "width": null,
                                "height": null,
                                "marker": null,
                                "traffic": null,
                                "marker_icon": null,
                                "controls": null,
                                "infowindow": null
                            },
                            "fieldLocationType": null,
                            "fieldSchoolLocation": null,
                            "paraType": "school_location"
                        }
                    },
                    "fieldSchoolWebpageAddress": "https://kutsehariduskeskus.ee/",
                    "fieldSpecialClass": null,
                    "fieldTeachingLanguage": {
                        "1689": "eesti keel",
                        "1691": "vene keel"
                    },
                    "uid": "1",
                    "title": "Ida-Virumaa Kutsehariduskeskus",
                    "created": "1538404211"
                }
            },
            "fieldIscedfBoard": {
                "2538": "Tehnika, tootmine ja ehitus"
            },
            "fieldIscedfDetailed": {
                "2568": "Ehitus ja tsiviilrajatised"
            },
            "fieldIscedfNarrow": {
                "2565": "Arhitektuur ja ehitus"
            },
            "fieldMetatags": null,
            "fieldMinimumRequiredEducation": {
                "3225": "põhiharidus (210)"
            },
            "fieldPracticalTrainingAmount": "15",
            "fieldSchoolAddress": "Tallinna mnt 13, Sillamäe linn, Ida-Viru maakond",
            "fieldSchoolSearchAddress": "Sillamäe linn, Ida-Viru maakond",
            "fieldSchoolWebsite": "https://kutsehariduskeskus.ee/",
            "fieldShortDescription": null,
            "fieldSpecialization": "määramata",
            "fieldStudyProgrammeLevel": {
                "2373": "Kutseõpe põhihariduse baasil"
            },
            "fieldStudyProgrammeType": {
                "644": "Kutsehariduse õppekava"
            },
            "fieldTeachingLanguage": {
                "1689": "eesti keel",
                "1691": "vene keel"
            },
            "uid": "1",
            "title": "Krohvija",
            "created": "1692400021"
        },
        {
            "nid": "16700",
            "path": "/erialad/v%C3%A4ikeettev%C3%B5tja-6",
            "id": "studyProgramme",
            "fieldAccreditationStatus": null,
            "fieldAccreditationValidUntil": null,
            "fieldAdmissionBeginDate": "1762812000",
            "fieldAdmissionEndDate": "1768168740",
            "fieldAdmissionId": "18411",
            "fieldAdmissionLink": "https://sais.ee/AdmissionSearch/View/18411",
            "fieldAmount": "90",
            "fieldAmountUnit": "EKAP",
            "fieldDegreeOrDiplomaAwarded": null,
            "fieldDuration": "18",
            "fieldEducationalInstitution": {
                "11345": {
                    "fieldEducationalInstitutionTy": {
                        "2364": "Kutseõppeasutus"
                    },
                    "fieldOwnershipType": {
                        "2033": "Riigiomandus"
                    },
                    "fieldSchoolContactEmail": "info@ivkhk.ee",
                    "fieldSchoolContactPhone": "3320381",
                    "fieldSchoolLocation": {
                        "8918": {
                            "fieldAddress": "Tallinna mnt 13, Sillamäe linn, Ida-Viru maakond",
                            "fieldCoordinates": {
                                "name": "Tallinna mnt 13, Sillamäe linn, Ida-Viru maakond",
                                "lat": "59.39098",
                                "lon": "27.793492",
                                "zoom": null,
                                "type": null,
                                "width": null,
                                "height": null,
                                "marker": null,
                                "traffic": null,
                                "marker_icon": null,
                                "controls": null,
                                "infowindow": null
                            },
                            "fieldLocationType": "L",
                            "fieldSchoolLocation": {
                                "485": "Sillamäe linn"
                            },
                            "paraType": "school_location"
                        },
                        "373035": {
                            "fieldAddress": "Kutse tn 13, Jõhvi linn, Jõhvi vald, Ida-Viru maakond",
                            "fieldCoordinates": {
                                "name": "Kutse tn 13, Jõhvi linn, Jõhvi vald, Ida-Viru maakond",
                                "lat": "59.360033",
                                "lon": "27.399148",
                                "zoom": null,
                                "type": null,
                                "width": null,
                                "height": null,
                                "marker": null,
                                "traffic": null,
                                "marker_icon": null,
                                "controls": null,
                                "infowindow": null
                            },
                            "fieldLocationType": null,
                            "fieldSchoolLocation": null,
                            "paraType": "school_location"
                        },
                        "373036": {
                            "fieldAddress": "Kreenholmi tn 45, Narva linn, Ida-Viru maakond",
                            "fieldCoordinates": {
                                "name": "Kreenholmi tn 45, Narva linn, Ida-Viru maakond",
                                "lat": "59.360678",
                                "lon": "28.188351",
                                "zoom": null,
                                "type": null,
                                "width": null,
                                "height": null,
                                "marker": null,
                                "traffic": null,
                                "marker_icon": null,
                                "controls": null,
                                "infowindow": null
                            },
                            "fieldLocationType": null,
                            "fieldSchoolLocation": null,
                            "paraType": "school_location"
                        }
                    },
                    "fieldSchoolWebpageAddress": "https://kutsehariduskeskus.ee/",
                    "fieldSpecialClass": null,
                    "fieldTeachingLanguage": {
                        "1689": "eesti keel",
                        "1691": "vene keel"
                    },
                    "uid": "1",
                    "title": "Ida-Virumaa Kutsehariduskeskus",
                    "created": "1538404211"
                }
            },
            "fieldIscedfBoard": {
                "2463": "Ärindus, haldus ja õigus"
            },
            "fieldIscedfDetailed": {
                "2469": "Juhtimine ja haldus"
            },
            "fieldIscedfNarrow": {
                "2464": "Ärindus ja haldus"
            },
            "fieldMetatags": null,
            "fieldMinimumRequiredEducation": {
                "3226": "üldkeskharidus (310)"
            },
            "fieldPracticalTrainingAmount": "23",
            "fieldSchoolAddress": "Tallinna mnt 13, Sillamäe linn, Ida-Viru maakond",
            "fieldSchoolSearchAddress": "Sillamäe linn, Ida-Viru maakond",
            "fieldSchoolWebsite": "https://kutsehariduskeskus.ee/",
            "fieldShortDescription": null,
            "fieldSpecialization": "määramata",
            "fieldStudyProgrammeLevel": {
                "2013": "Kutseõpe keskhariduse baasil"
            },
            "fieldStudyProgrammeType": {
                "644": "Kutsehariduse õppekava"
            },
            "fieldTeachingLanguage": {
                "1689": "eesti keel",
                "1691": "vene keel"
            },
            "uid": "1",
            "title": "Väikeettevõtja",
            "created": "1654729680"
        },
        {
            "nid": "16702",
            "path": "/erialad/k%C3%BCtte-ja-jahutuss%C3%BCsteemide-lukksepp-3",
            "id": "studyProgramme",
            "fieldAccreditationStatus": null,
            "fieldAccreditationValidUntil": null,
            "fieldAdmissionBeginDate": "1762812000",
            "fieldAdmissionEndDate": "1768168740",
            "fieldAdmissionId": "18413",
            "fieldAdmissionLink": "https://sais.ee/AdmissionSearch/View/18413",
            "fieldAmount": "60",
            "fieldAmountUnit": "EKAP",
            "fieldDegreeOrDiplomaAwarded": null,
            "fieldDuration": "12",
            "fieldEducationalInstitution": {
                "11345": {
                    "fieldEducationalInstitutionTy": {
                        "2364": "Kutseõppeasutus"
                    },
                    "fieldOwnershipType": {
                        "2033": "Riigiomandus"
                    },
                    "fieldSchoolContactEmail": "info@ivkhk.ee",
                    "fieldSchoolContactPhone": "3320381",
                    "fieldSchoolLocation": {
                        "8918": {
                            "fieldAddress": "Tallinna mnt 13, Sillamäe linn, Ida-Viru maakond",
                            "fieldCoordinates": {
                                "name": "Tallinna mnt 13, Sillamäe linn, Ida-Viru maakond",
                                "lat": "59.39098",
                                "lon": "27.793492",
                                "zoom": null,
                                "type": null,
                                "width": null,
                                "height": null,
                                "marker": null,
                                "traffic": null,
                                "marker_icon": null,
                                "controls": null,
                                "infowindow": null
                            },
                            "fieldLocationType": "L",
                            "fieldSchoolLocation": {
                                "485": "Sillamäe linn"
                            },
                            "paraType": "school_location"
                        },
                        "373035": {
                            "fieldAddress": "Kutse tn 13, Jõhvi linn, Jõhvi vald, Ida-Viru maakond",
                            "fieldCoordinates": {
                                "name": "Kutse tn 13, Jõhvi linn, Jõhvi vald, Ida-Viru maakond",
                                "lat": "59.360033",
                                "lon": "27.399148",
                                "zoom": null,
                                "type": null,
                                "width": null,
                                "height": null,
                                "marker": null,
                                "traffic": null,
                                "marker_icon": null,
                                "controls": null,
                                "infowindow": null
                            },
                            "fieldLocationType": null,
                            "fieldSchoolLocation": null,
                            "paraType": "school_location"
                        },
                        "373036": {
                            "fieldAddress": "Kreenholmi tn 45, Narva linn, Ida-Viru maakond",
                            "fieldCoordinates": {
                                "name": "Kreenholmi tn 45, Narva linn, Ida-Viru maakond",
                                "lat": "59.360678",
                                "lon": "28.188351",
                                "zoom": null,
                                "type": null,
                                "width": null,
                                "height": null,
                                "marker": null,
                                "traffic": null,
                                "marker_icon": null,
                                "controls": null,
                                "infowindow": null
                            },
                            "fieldLocationType": null,
                            "fieldSchoolLocation": null,
                            "paraType": "school_location"
                        }
                    },
                    "fieldSchoolWebpageAddress": "https://kutsehariduskeskus.ee/",
                    "fieldSpecialClass": null,
                    "fieldTeachingLanguage": {
                        "1689": "eesti keel",
                        "1691": "vene keel"
                    },
                    "uid": "1",
                    "title": "Ida-Virumaa Kutsehariduskeskus",
                    "created": "1538404211"
                }
            },
            "fieldIscedfBoard": {
                "2538": "Tehnika, tootmine ja ehitus"
            },
            "fieldIscedfDetailed": {
                "2568": "Ehitus ja tsiviilrajatised"
            },
            "fieldIscedfNarrow": {
                "2565": "Arhitektuur ja ehitus"
            },
            "fieldMetatags": null,
            "fieldMinimumRequiredEducation": {
                "3225": "põhiharidus (210)"
            },
            "fieldPracticalTrainingAmount": "15",
            "fieldSchoolAddress": "Tallinna mnt 13, Sillamäe linn, Ida-Viru maakond",
            "fieldSchoolSearchAddress": "Sillamäe linn, Ida-Viru maakond",
            "fieldSchoolWebsite": "https://kutsehariduskeskus.ee/",
            "fieldShortDescription": null,
            "fieldSpecialization": "määramata",
            "fieldStudyProgrammeLevel": {
                "2373": "Kutseõpe põhihariduse baasil"
            },
            "fieldStudyProgrammeType": {
                "644": "Kutsehariduse õppekava"
            },
            "fieldTeachingLanguage": {
                "1689": "eesti keel",
                "1691": "vene keel"
            },
            "uid": "1",
            "title": "Kütte- ja jahutussüsteemide lukksepp",
            "created": "1654729680"
        },
        {
            "nid": "16781",
            "path": "/erialad/mootors%C3%B5idukitehnik-spetsialiseerumine-s%C3%B5iduautotehnik-2",
            "id": "studyProgramme",
            "fieldAccreditationStatus": null,
            "fieldAccreditationValidUntil": null,
            "fieldAdmissionBeginDate": "1762812000",
            "fieldAdmissionEndDate": "1768168740",
            "fieldAdmissionId": "18412",
            "fieldAdmissionLink": "https://sais.ee/AdmissionSearch/View/18412",
            "fieldAmount": "120",
            "fieldAmountUnit": "EKAP",
            "fieldDegreeOrDiplomaAwarded": null,
            "fieldDuration": "24",
            "fieldEducationalInstitution": {
                "11345": {
                    "fieldEducationalInstitutionTy": {
                        "2364": "Kutseõppeasutus"
                    },
                    "fieldOwnershipType": {
                        "2033": "Riigiomandus"
                    },
                    "fieldSchoolContactEmail": "info@ivkhk.ee",
                    "fieldSchoolContactPhone": "3320381",
                    "fieldSchoolLocation": {
                        "8918": {
                            "fieldAddress": "Tallinna mnt 13, Sillamäe linn, Ida-Viru maakond",
                            "fieldCoordinates": {
                                "name": "Tallinna mnt 13, Sillamäe linn, Ida-Viru maakond",
                                "lat": "59.39098",
                                "lon": "27.793492",
                                "zoom": null,
                                "type": null,
                                "width": null,
                                "height": null,
                                "marker": null,
                                "traffic": null,
                                "marker_icon": null,
                                "controls": null,
                                "infowindow": null
                            },
                            "fieldLocationType": "L",
                            "fieldSchoolLocation": {
                                "485": "Sillamäe linn"
                            },
                            "paraType": "school_location"
                        },
                        "373035": {
                            "fieldAddress": "Kutse tn 13, Jõhvi linn, Jõhvi vald, Ida-Viru maakond",
                            "fieldCoordinates": {
                                "name": "Kutse tn 13, Jõhvi linn, Jõhvi vald, Ida-Viru maakond",
                                "lat": "59.360033",
                                "lon": "27.399148",
                                "zoom": null,
                                "type": null,
                                "width": null,
                                "height": null,
                                "marker": null,
                                "traffic": null,
                                "marker_icon": null,
                                "controls": null,
                                "infowindow": null
                            },
                            "fieldLocationType": null,
                            "fieldSchoolLocation": null,
                            "paraType": "school_location"
                        },
                        "373036": {
                            "fieldAddress": "Kreenholmi tn 45, Narva linn, Ida-Viru maakond",
                            "fieldCoordinates": {
                                "name": "Kreenholmi tn 45, Narva linn, Ida-Viru maakond",
                                "lat": "59.360678",
                                "lon": "28.188351",
                                "zoom": null,
                                "type": null,
                                "width": null,
                                "height": null,
                                "marker": null,
                                "traffic": null,
                                "marker_icon": null,
                                "controls": null,
                                "infowindow": null
                            },
                            "fieldLocationType": null,
                            "fieldSchoolLocation": null,
                            "paraType": "school_location"
                        }
                    },
                    "fieldSchoolWebpageAddress": "https://kutsehariduskeskus.ee/",
                    "fieldSpecialClass": null,
                    "fieldTeachingLanguage": {
                        "1689": "eesti keel",
                        "1691": "vene keel"
                    },
                    "uid": "1",
                    "title": "Ida-Virumaa Kutsehariduskeskus",
                    "created": "1538404211"
                }
            },
            "fieldIscedfBoard": {
                "2538": "Tehnika, tootmine ja ehitus"
            },
            "fieldIscedfDetailed": {
                "2550": "Mootorliikurid, laevandus ja lennundustehnika"
            },
            "fieldIscedfNarrow": {
                "2539": "Tehnikaalad"
            },
            "fieldMetatags": null,
            "fieldMinimumRequiredEducation": {
                "3225": "põhiharidus (210)"
            },
            "fieldPracticalTrainingAmount": "40",
            "fieldSchoolAddress": "Tallinna mnt 13, Sillamäe linn, Ida-Viru maakond",
            "fieldSchoolSearchAddress": "Sillamäe linn, Ida-Viru maakond",
            "fieldSchoolWebsite": "https://kutsehariduskeskus.ee/",
            "fieldShortDescription": null,
            "fieldSpecialization": "määramata",
            "fieldStudyProgrammeLevel": {
                "2373": "Kutseõpe põhihariduse baasil"
            },
            "fieldStudyProgrammeType": {
                "644": "Kutsehariduse õppekava"
            },
            "fieldTeachingLanguage": {
                "1689": "eesti keel",
                "1691": "vene keel"
            },
            "uid": "1",
            "title": "Mootorsõidukitehnik (spetsialiseerumine sõiduautotehnik)",
            "created": "1655334540"
        },
        {
            "nid": "17822",
            "path": "/erialad/kokk-62",
            "id": "studyProgramme",
            "fieldAccreditationStatus": null,
            "fieldAccreditationValidUntil": null,
            "fieldAdmissionBeginDate": "1762812000",
            "fieldAdmissionEndDate": "1768168740",
            "fieldAdmissionId": "18396",
            "fieldAdmissionLink": "https://sais.ee/AdmissionSearch/View/18396",
            "fieldAmount": "120",
            "fieldAmountUnit": "EKAP",
            "fieldDegreeOrDiplomaAwarded": null,
            "fieldDuration": "24",
            "fieldEducationalInstitution": {
                "11345": {
                    "fieldEducationalInstitutionTy": {
                        "2364": "Kutseõppeasutus"
                    },
                    "fieldOwnershipType": {
                        "2033": "Riigiomandus"
                    },
                    "fieldSchoolContactEmail": "info@ivkhk.ee",
                    "fieldSchoolContactPhone": "3320381",
                    "fieldSchoolLocation": {
                        "8918": {
                            "fieldAddress": "Tallinna mnt 13, Sillamäe linn, Ida-Viru maakond",
                            "fieldCoordinates": {
                                "name": "Tallinna mnt 13, Sillamäe linn, Ida-Viru maakond",
                                "lat": "59.39098",
                                "lon": "27.793492",
                                "zoom": null,
                                "type": null,
                                "width": null,
                                "height": null,
                                "marker": null,
                                "traffic": null,
                                "marker_icon": null,
                                "controls": null,
                                "infowindow": null
                            },
                            "fieldLocationType": "L",
                            "fieldSchoolLocation": {
                                "485": "Sillamäe linn"
                            },
                            "paraType": "school_location"
                        },
                        "373035": {
                            "fieldAddress": "Kutse tn 13, Jõhvi linn, Jõhvi vald, Ida-Viru maakond",
                            "fieldCoordinates": {
                                "name": "Kutse tn 13, Jõhvi linn, Jõhvi vald, Ida-Viru maakond",
                                "lat": "59.360033",
                                "lon": "27.399148",
                                "zoom": null,
                                "type": null,
                                "width": null,
                                "height": null,
                                "marker": null,
                                "traffic": null,
                                "marker_icon": null,
                                "controls": null,
                                "infowindow": null
                            },
                            "fieldLocationType": null,
                            "fieldSchoolLocation": null,
                            "paraType": "school_location"
                        },
                        "373036": {
                            "fieldAddress": "Kreenholmi tn 45, Narva linn, Ida-Viru maakond",
                            "fieldCoordinates": {
                                "name": "Kreenholmi tn 45, Narva linn, Ida-Viru maakond",
                                "lat": "59.360678",
                                "lon": "28.188351",
                                "zoom": null,
                                "type": null,
                                "width": null,
                                "height": null,
                                "marker": null,
                                "traffic": null,
                                "marker_icon": null,
                                "controls": null,
                                "infowindow": null
                            },
                            "fieldLocationType": null,
                            "fieldSchoolLocation": null,
                            "paraType": "school_location"
                        }
                    },
                    "fieldSchoolWebpageAddress": "https://kutsehariduskeskus.ee/",
                    "fieldSpecialClass": null,
                    "fieldTeachingLanguage": {
                        "1689": "eesti keel",
                        "1691": "vene keel"
                    },
                    "uid": "1",
                    "title": "Ida-Virumaa Kutsehariduskeskus",
                    "created": "1538404211"
                }
            },
            "fieldIscedfBoard": {
                "2632": "Teenindus"
            },
            "fieldIscedfDetailed": {
                "2638": "Majutamine ja toitlustamine"
            },
            "fieldIscedfNarrow": {
                "2633": "Isikuteenindus"
            },
            "fieldMetatags": null,
            "fieldMinimumRequiredEducation": {
                "3225": "põhiharidus (210)"
            },
            "fieldPracticalTrainingAmount": "30",
            "fieldSchoolAddress": "Tallinna mnt 13, Sillamäe linn, Ida-Viru maakond",
            "fieldSchoolSearchAddress": "Sillamäe linn, Ida-Viru maakond",
            "fieldSchoolWebsite": "https://kutsehariduskeskus.ee/",
            "fieldShortDescription": null,
            "fieldSpecialization": "määramata",
            "fieldStudyProgrammeLevel": {
                "2373": "Kutseõpe põhihariduse baasil"
            },
            "fieldStudyProgrammeType": {
                "644": "Kutsehariduse õppekava"
            },
            "fieldTeachingLanguage": {
                "1689": "eesti keel",
                "1691": "vene keel"
            },
            "uid": "1",
            "title": "Kokk",
            "created": "1677802021"
        },
        {
            "nid": "281373",
            "path": "/erialad/cnc-freespingi-operaator-3",
            "id": "studyProgramme",
            "fieldAccreditationStatus": null,
            "fieldAccreditationValidUntil": null,
            "fieldAdmissionBeginDate": "1762812000",
            "fieldAdmissionEndDate": "1768168740",
            "fieldAdmissionId": "18414",
            "fieldAdmissionLink": "https://sais.ee/AdmissionSearch/View/18414",
            "fieldAmount": "60",
            "fieldAmountUnit": "EKAP",
            "fieldDegreeOrDiplomaAwarded": null,
            "fieldDuration": "12",
            "fieldEducationalInstitution": {
                "11345": {
                    "fieldEducationalInstitutionTy": {
                        "2364": "Kutseõppeasutus"
                    },
                    "fieldOwnershipType": {
                        "2033": "Riigiomandus"
                    },
                    "fieldSchoolContactEmail": "info@ivkhk.ee",
                    "fieldSchoolContactPhone": "3320381",
                    "fieldSchoolLocation": {
                        "8918": {
                            "fieldAddress": "Tallinna mnt 13, Sillamäe linn, Ida-Viru maakond",
                            "fieldCoordinates": {
                                "name": "Tallinna mnt 13, Sillamäe linn, Ida-Viru maakond",
                                "lat": "59.39098",
                                "lon": "27.793492",
                                "zoom": null,
                                "type": null,
                                "width": null,
                                "height": null,
                                "marker": null,
                                "traffic": null,
                                "marker_icon": null,
                                "controls": null,
                                "infowindow": null
                            },
                            "fieldLocationType": "L",
                            "fieldSchoolLocation": {
                                "485": "Sillamäe linn"
                            },
                            "paraType": "school_location"
                        },
                        "373035": {
                            "fieldAddress": "Kutse tn 13, Jõhvi linn, Jõhvi vald, Ida-Viru maakond",
                            "fieldCoordinates": {
                                "name": "Kutse tn 13, Jõhvi linn, Jõhvi vald, Ida-Viru maakond",
                                "lat": "59.360033",
                                "lon": "27.399148",
                                "zoom": null,
                                "type": null,
                                "width": null,
                                "height": null,
                                "marker": null,
                                "traffic": null,
                                "marker_icon": null,
                                "controls": null,
                                "infowindow": null
                            },
                            "fieldLocationType": null,
                            "fieldSchoolLocation": null,
                            "paraType": "school_location"
                        },
                        "373036": {
                            "fieldAddress": "Kreenholmi tn 45, Narva linn, Ida-Viru maakond",
                            "fieldCoordinates": {
                                "name": "Kreenholmi tn 45, Narva linn, Ida-Viru maakond",
                                "lat": "59.360678",
                                "lon": "28.188351",
                                "zoom": null,
                                "type": null,
                                "width": null,
                                "height": null,
                                "marker": null,
                                "traffic": null,
                                "marker_icon": null,
                                "controls": null,
                                "infowindow": null
                            },
                            "fieldLocationType": null,
                            "fieldSchoolLocation": null,
                            "paraType": "school_location"
                        }
                    },
                    "fieldSchoolWebpageAddress": "https://kutsehariduskeskus.ee/",
                    "fieldSpecialClass": null,
                    "fieldTeachingLanguage": {
                        "1689": "eesti keel",
                        "1691": "vene keel"
                    },
                    "uid": "1",
                    "title": "Ida-Virumaa Kutsehariduskeskus",
                    "created": "1538404211"
                }
            },
            "fieldIscedfBoard": {
                "2538": "Tehnika, tootmine ja ehitus"
            },
            "fieldIscedfDetailed": {
                "2548": "Mehaanika ja metallitöö"
            },
            "fieldIscedfNarrow": {
                "2539": "Tehnikaalad"
            },
            "fieldMetatags": null,
            "fieldMinimumRequiredEducation": {
                "3225": "põhiharidus (210)"
            },
            "fieldPracticalTrainingAmount": "28",
            "fieldSchoolAddress": "Tallinna mnt 13, Sillamäe linn, Ida-Viru maakond",
            "fieldSchoolSearchAddress": "Sillamäe linn, Ida-Viru maakond",
            "fieldSchoolWebsite": "https://kutsehariduskeskus.ee/",
            "fieldShortDescription": null,
            "fieldSpecialization": "määramata",
            "fieldStudyProgrammeLevel": {
                "2373": "Kutseõpe põhihariduse baasil"
            },
            "fieldStudyProgrammeType": {
                "644": "Kutsehariduse õppekava"
            },
            "fieldTeachingLanguage": {
                "1689": "eesti keel",
                "1691": "vene keel"
            },
            "uid": "1",
            "title": "CNC freespingi operaator",
            "created": "1688080081"
        },
        {
            "nid": "37393597",
            "path": "/erialad/infoturbespetsialist",
            "id": "studyProgramme",
            "fieldAccreditationStatus": null,
            "fieldAccreditationValidUntil": null,
            "fieldAdmissionBeginDate": "1762812000",
            "fieldAdmissionEndDate": "1768168740",
            "fieldAdmissionId": "18392",
            "fieldAdmissionLink": "https://sais.ee/AdmissionSearch/View/18392",
            "fieldAmount": "60",
            "fieldAmountUnit": "EKAP",
            "fieldDegreeOrDiplomaAwarded": null,
            "fieldDuration": "12",
            "fieldEducationalInstitution": {
                "11345": {
                    "fieldEducationalInstitutionTy": {
                        "2364": "Kutseõppeasutus"
                    },
                    "fieldOwnershipType": {
                        "2033": "Riigiomandus"
                    },
                    "fieldSchoolContactEmail": "info@ivkhk.ee",
                    "fieldSchoolContactPhone": "3320381",
                    "fieldSchoolLocation": {
                        "8918": {
                            "fieldAddress": "Tallinna mnt 13, Sillamäe linn, Ida-Viru maakond",
                            "fieldCoordinates": {
                                "name": "Tallinna mnt 13, Sillamäe linn, Ida-Viru maakond",
                                "lat": "59.39098",
                                "lon": "27.793492",
                                "zoom": null,
                                "type": null,
                                "width": null,
                                "height": null,
                                "marker": null,
                                "traffic": null,
                                "marker_icon": null,
                                "controls": null,
                                "infowindow": null
                            },
                            "fieldLocationType": "L",
                            "fieldSchoolLocation": {
                                "485": "Sillamäe linn"
                            },
                            "paraType": "school_location"
                        },
                        "373035": {
                            "fieldAddress": "Kutse tn 13, Jõhvi linn, Jõhvi vald, Ida-Viru maakond",
                            "fieldCoordinates": {
                                "name": "Kutse tn 13, Jõhvi linn, Jõhvi vald, Ida-Viru maakond",
                                "lat": "59.360033",
                                "lon": "27.399148",
                                "zoom": null,
                                "type": null,
                                "width": null,
                                "height": null,
                                "marker": null,
                                "traffic": null,
                                "marker_icon": null,
                                "controls": null,
                                "infowindow": null
                            },
                            "fieldLocationType": null,
                            "fieldSchoolLocation": null,
                            "paraType": "school_location"
                        },
                        "373036": {
                            "fieldAddress": "Kreenholmi tn 45, Narva linn, Ida-Viru maakond",
                            "fieldCoordinates": {
                                "name": "Kreenholmi tn 45, Narva linn, Ida-Viru maakond",
                                "lat": "59.360678",
                                "lon": "28.188351",
                                "zoom": null,
                                "type": null,
                                "width": null,
                                "height": null,
                                "marker": null,
                                "traffic": null,
                                "marker_icon": null,
                                "controls": null,
                                "infowindow": null
                            },
                            "fieldLocationType": null,
                            "fieldSchoolLocation": null,
                            "paraType": "school_location"
                        }
                    },
                    "fieldSchoolWebpageAddress": "https://kutsehariduskeskus.ee/",
                    "fieldSpecialClass": null,
                    "fieldTeachingLanguage": {
                        "1689": "eesti keel",
                        "1691": "vene keel"
                    },
                    "uid": "1",
                    "title": "Ida-Virumaa Kutsehariduskeskus",
                    "created": "1538404211"
                }
            },
            "fieldIscedfBoard": {
                "2525": "Informatsiooni- ja kommunikatsioonitehnoloogiad"
            },
            "fieldIscedfDetailed": {
                "2529": "Andmebaaside ja võrgu disain ning haldus"
            },
            "fieldIscedfNarrow": {
                "2526": "Informatsiooni- ja kommunikatsioonitehnoloogiad"
            },
            "fieldMetatags": null,
            "fieldMinimumRequiredEducation": {
                "3226": "üldkeskharidus (310)"
            },
            "fieldPracticalTrainingAmount": "15",
            "fieldSchoolAddress": "Tallinna mnt 13, Sillamäe linn, Ida-Viru maakond",
            "fieldSchoolSearchAddress": "Sillamäe linn, Ida-Viru maakond",
            "fieldSchoolWebsite": "https://kutsehariduskeskus.ee/",
            "fieldShortDescription": null,
            "fieldSpecialization": "määramata",
            "fieldStudyProgrammeLevel": {
                "2013": "Kutseõpe keskhariduse baasil"
            },
            "fieldStudyProgrammeType": {
                "644": "Kutsehariduse õppekava"
            },
            "fieldTeachingLanguage": {
                "1689": "eesti keel",
                "1691": "vene keel"
            },
            "uid": "1",
            "title": "Infoturbespetsialist",
            "created": "1715901121"
        },
        {
            "nid": "37400296",
            "path": "/erialad/p%C3%A4ikeseelektris%C3%BCsteemide-paigaldaja-0",
            "id": "studyProgramme",
            "fieldAccreditationStatus": null,
            "fieldAccreditationValidUntil": null,
            "fieldAdmissionBeginDate": "1762812000",
            "fieldAdmissionEndDate": "1768168740",
            "fieldAdmissionId": "18418",
            "fieldAdmissionLink": "https://sais.ee/AdmissionSearch/View/18418",
            "fieldAmount": "30",
            "fieldAmountUnit": "EKAP",
            "fieldDegreeOrDiplomaAwarded": null,
            "fieldDuration": "6",
            "fieldEducationalInstitution": {
                "11345": {
                    "fieldEducationalInstitutionTy": {
                        "2364": "Kutseõppeasutus"
                    },
                    "fieldOwnershipType": {
                        "2033": "Riigiomandus"
                    },
                    "fieldSchoolContactEmail": "info@ivkhk.ee",
                    "fieldSchoolContactPhone": "3320381",
                    "fieldSchoolLocation": {
                        "8918": {
                            "fieldAddress": "Tallinna mnt 13, Sillamäe linn, Ida-Viru maakond",
                            "fieldCoordinates": {
                                "name": "Tallinna mnt 13, Sillamäe linn, Ida-Viru maakond",
                                "lat": "59.39098",
                                "lon": "27.793492",
                                "zoom": null,
                                "type": null,
                                "width": null,
                                "height": null,
                                "marker": null,
                                "traffic": null,
                                "marker_icon": null,
                                "controls": null,
                                "infowindow": null
                            },
                            "fieldLocationType": "L",
                            "fieldSchoolLocation": {
                                "485": "Sillamäe linn"
                            },
                            "paraType": "school_location"
                        },
                        "373035": {
                            "fieldAddress": "Kutse tn 13, Jõhvi linn, Jõhvi vald, Ida-Viru maakond",
                            "fieldCoordinates": {
                                "name": "Kutse tn 13, Jõhvi linn, Jõhvi vald, Ida-Viru maakond",
                                "lat": "59.360033",
                                "lon": "27.399148",
                                "zoom": null,
                                "type": null,
                                "width": null,
                                "height": null,
                                "marker": null,
                                "traffic": null,
                                "marker_icon": null,
                                "controls": null,
                                "infowindow": null
                            },
                            "fieldLocationType": null,
                            "fieldSchoolLocation": null,
                            "paraType": "school_location"
                        },
                        "373036": {
                            "fieldAddress": "Kreenholmi tn 45, Narva linn, Ida-Viru maakond",
                            "fieldCoordinates": {
                                "name": "Kreenholmi tn 45, Narva linn, Ida-Viru maakond",
                                "lat": "59.360678",
                                "lon": "28.188351",
                                "zoom": null,
                                "type": null,
                                "width": null,
                                "height": null,
                                "marker": null,
                                "traffic": null,
                                "marker_icon": null,
                                "controls": null,
                                "infowindow": null
                            },
                            "fieldLocationType": null,
                            "fieldSchoolLocation": null,
                            "paraType": "school_location"
                        }
                    },
                    "fieldSchoolWebpageAddress": "https://kutsehariduskeskus.ee/",
                    "fieldSpecialClass": null,
                    "fieldTeachingLanguage": {
                        "1689": "eesti keel",
                        "1691": "vene keel"
                    },
                    "uid": "1",
                    "title": "Ida-Virumaa Kutsehariduskeskus",
                    "created": "1538404211"
                }
            },
            "fieldIscedfBoard": {
                "2538": "Tehnika, tootmine ja ehitus"
            },
            "fieldIscedfDetailed": {
                "2544": "Elektrienergia ja energeetika"
            },
            "fieldIscedfNarrow": {
                "2539": "Tehnikaalad"
            },
            "fieldMetatags": null,
            "fieldMinimumRequiredEducation": {
                "3225": "põhiharidus (210)"
            },
            "fieldPracticalTrainingAmount": "10",
            "fieldSchoolAddress": "Tallinna mnt 13, Sillamäe linn, Ida-Viru maakond",
            "fieldSchoolSearchAddress": "Sillamäe linn, Ida-Viru maakond",
            "fieldSchoolWebsite": "https://kutsehariduskeskus.ee/",
            "fieldShortDescription": null,
            "fieldSpecialization": "määramata",
            "fieldStudyProgrammeLevel": {
                "2373": "Kutseõpe põhihariduse baasil"
            },
            "fieldStudyProgrammeType": {
                "644": "Kutsehariduse õppekava"
            },
            "fieldTeachingLanguage": {
                "1689": "eesti keel",
                "1691": "vene keel"
            },
            "uid": "1",
            "title": "Päikeseelektrisüsteemide paigaldaja",
            "created": "1733443921"
        },
        {
            "nid": "37400313",
            "path": "/erialad/metalltoodete-koostaja",
            "id": "studyProgramme",
            "fieldAccreditationStatus": null,
            "fieldAccreditationValidUntil": null,
            "fieldAdmissionBeginDate": "1762812000",
            "fieldAdmissionEndDate": "1768168740",
            "fieldAdmissionId": "18401",
            "fieldAdmissionLink": "https://sais.ee/AdmissionSearch/View/18401",
            "fieldAmount": "60",
            "fieldAmountUnit": "EKAP",
            "fieldDegreeOrDiplomaAwarded": null,
            "fieldDuration": "12",
            "fieldEducationalInstitution": {
                "11345": {
                    "fieldEducationalInstitutionTy": {
                        "2364": "Kutseõppeasutus"
                    },
                    "fieldOwnershipType": {
                        "2033": "Riigiomandus"
                    },
                    "fieldSchoolContactEmail": "info@ivkhk.ee",
                    "fieldSchoolContactPhone": "3320381",
                    "fieldSchoolLocation": {
                        "8918": {
                            "fieldAddress": "Tallinna mnt 13, Sillamäe linn, Ida-Viru maakond",
                            "fieldCoordinates": {
                                "name": "Tallinna mnt 13, Sillamäe linn, Ida-Viru maakond",
                                "lat": "59.39098",
                                "lon": "27.793492",
                                "zoom": null,
                                "type": null,
                                "width": null,
                                "height": null,
                                "marker": null,
                                "traffic": null,
                                "marker_icon": null,
                                "controls": null,
                                "infowindow": null
                            },
                            "fieldLocationType": "L",
                            "fieldSchoolLocation": {
                                "485": "Sillamäe linn"
                            },
                            "paraType": "school_location"
                        },
                        "373035": {
                            "fieldAddress": "Kutse tn 13, Jõhvi linn, Jõhvi vald, Ida-Viru maakond",
                            "fieldCoordinates": {
                                "name": "Kutse tn 13, Jõhvi linn, Jõhvi vald, Ida-Viru maakond",
                                "lat": "59.360033",
                                "lon": "27.399148",
                                "zoom": null,
                                "type": null,
                                "width": null,
                                "height": null,
                                "marker": null,
                                "traffic": null,
                                "marker_icon": null,
                                "controls": null,
                                "infowindow": null
                            },
                            "fieldLocationType": null,
                            "fieldSchoolLocation": null,
                            "paraType": "school_location"
                        },
                        "373036": {
                            "fieldAddress": "Kreenholmi tn 45, Narva linn, Ida-Viru maakond",
                            "fieldCoordinates": {
                                "name": "Kreenholmi tn 45, Narva linn, Ida-Viru maakond",
                                "lat": "59.360678",
                                "lon": "28.188351",
                                "zoom": null,
                                "type": null,
                                "width": null,
                                "height": null,
                                "marker": null,
                                "traffic": null,
                                "marker_icon": null,
                                "controls": null,
                                "infowindow": null
                            },
                            "fieldLocationType": null,
                            "fieldSchoolLocation": null,
                            "paraType": "school_location"
                        }
                    },
                    "fieldSchoolWebpageAddress": "https://kutsehariduskeskus.ee/",
                    "fieldSpecialClass": null,
                    "fieldTeachingLanguage": {
                        "1689": "eesti keel",
                        "1691": "vene keel"
                    },
                    "uid": "1",
                    "title": "Ida-Virumaa Kutsehariduskeskus",
                    "created": "1538404211"
                }
            },
            "fieldIscedfBoard": {
                "2538": "Tehnika, tootmine ja ehitus"
            },
            "fieldIscedfDetailed": {
                "2548": "Mehaanika ja metallitöö"
            },
            "fieldIscedfNarrow": {
                "2539": "Tehnikaalad"
            },
            "fieldMetatags": null,
            "fieldMinimumRequiredEducation": {
                "3230": "ei oma haridust (993)"
            },
            "fieldPracticalTrainingAmount": "15",
            "fieldSchoolAddress": "Tallinna mnt 13, Sillamäe linn, Ida-Viru maakond",
            "fieldSchoolSearchAddress": "Sillamäe linn, Ida-Viru maakond",
            "fieldSchoolWebsite": "https://kutsehariduskeskus.ee/",
            "fieldShortDescription": null,
            "fieldSpecialization": null,
            "fieldStudyProgrammeLevel": {
                "2372": "Põhihariduse nõudeta kutseõpe"
            },
            "fieldStudyProgrammeType": {
                "644": "Kutsehariduse õppekava"
            },
            "fieldTeachingLanguage": {
                "1689": "eesti keel",
                "1691": "vene keel"
            },
            "uid": "1",
            "title": "Metalltoodete koostaja",
            "created": "1734653641"
        }
    ],
    "count": 3876,
    "field_neurotolge_state": "translated_with_neurotolge"
}